humanice/__init__.py
humanice/filesize.py
humanice/i18n.py
humanice/locale/de_DE/LC_MESSAGES/humanice.mo
humanice/locale/de_DE/LC_MESSAGES/humanice.po
humanice/locale/fi_FI/LC_MESSAGES/humanice.mo
humanice/locale/fi_FI/LC_MESSAGES/humanice.po
humanice/locale/fr_FR/LC_MESSAGES/humanice.mo
humanice/locale/fr_FR/LC_MESSAGES/humanice.po
humanice/locale/id_ID/LC_MESSAGES/humanice.mo
humanice/locale/id_ID/LC_MESSAGES/humanice.po
humanice/locale/it_IT/LC_MESSAGES/humanice.mo
humanice/locale/it_IT/LC_MESSAGES/humanice.po
humanice/locale/ja_JP/LC_MESSAGES/humanice.mo
humanice/locale/ja_JP/LC_MESSAGES/humanice.po
humanice/locale/ko_KR/LC_MESSAGES/humanice.mo
humanice/locale/ko_KR/LC_MESSAGES/humanice.po
humanice/locale/nl_NL/LC_MESSAGES/humanice.mo
humanice/locale/nl_NL/LC_MESSAGES/humanice.po
humanice/locale/pt_BR/LC_MESSAGES/humanice.mo
humanice/locale/pt_BR/LC_MESSAGES/humanice.po
humanice/locale/ru_RU/LC_MESSAGES/humanice.mo
humanice/locale/ru_RU/LC_MESSAGES/humanice.po
humanice/locale/sk_SK/LC_MESSAGES/humanice.mo
humanice/locale/sk_SK/LC_MESSAGES/humanice.po
humanice/locale/tr_TR/LC_MESSAGES/humanice.mo
humanice/locale/tr_TR/LC_MESSAGES/humanice.po
humanice/locale/vi_VI/LC_MESSAGES/humanice.mo
humanice/locale/vi_VI/LC_MESSAGES/humanice.po
humanice/locale/zh_CN/LC_MESSAGES/humanice.mo
humanice/locale/zh_CN/LC_MESSAGES/humanice.po
humanice/number.py
humanice/time.py
humanice-1.1.0.dist-info/LICENSE.md
humanice-1.1.0.dist-info/WHEEL
humanice-1.1.0.dist-info/METADATA
humanice-1.1.0.dist-info/RECORD
