Metadata-Version: 2.1
Name: humanice
Version: 1.1.0
Summary: Nice humanize functions for Python
Home-page: https://github.com/timwedde/humanice
License: MIT
Author: Tim Wedde
Author-email: timwedde@icloud.com
Requires-Python: >=3.6,<4.0
Classifier: License :: OSI Approved :: MIT License
Classifier: Programming Language :: Python :: 3
Classifier: Programming Language :: Python :: 3.6
Classifier: Programming Language :: Python :: 3.7
Classifier: Programming Language :: Python :: 3.8
Project-URL: Repository, https://github.com/timwedde/humanice
